ctextinctPackage/__init__.py
ctextinctPackage/__main__.py
ctextinctPackage/controller.py
ctextinctPackage/model_.py
ctextinctPackage/parse_and_forum.py
ctextinctPackage/train.py
ctextinctPackage/view.py
ctextinct-6.3.1.dist-info/LICENCE
ctextinct-6.3.1.dist-info/METADATA
ctextinct-6.3.1.dist-info/WHEEL
ctextinct-6.3.1.dist-info/entry_points.txt
ctextinct-6.3.1.dist-info/top_level.txt
ctextinct-6.3.1.dist-info/RECORD
